wasmvm/__init__.py
wasmvm/functions.py
wasmvm/lib.py
wasmvm/observers.py
wasmvm/shared.py
wasmvm/virtual_machine.py
WasmVM-0.1.0.dist-info/LICENSE
WasmVM-0.1.0.dist-info/METADATA
WasmVM-0.1.0.dist-info/WHEEL
WasmVM-0.1.0.dist-info/top_level.txt
WasmVM-0.1.0.dist-info/RECORD
