Metadata-Version: 2.1
Name: WasmVM
Version: 0.1.0
Summary: A stack-based virtual machine for learning about WebAssembly
Author: chris boette
Author-email: chris boette <chrisbodhi@gmail.com>
License: BSD-3-Clause
Project-URL: Homepage, https://github.com/chrisbodhi/WasmVM.py
Project-URL: Issues, https://github.com/chrisbodhi/WasmVM.py/issues
Classifier: Programming Language :: Python :: 3
Requires-Python: >=3.12, <4
License-File: LICENSE
